querystar/__init__.py
querystar/actions/__init__.py
querystar/actions/google_sheets/__init__.py
querystar/actions/slack/__init__.py
querystar/actions/slack/add_direct_message.py
querystar/actions/slack/add_message.py
querystar/actions/slack/find.py
querystar/cli.py
querystar/client.py
querystar/commands/__init__.py
querystar/commands/run/__init__.py
querystar/commands/run/utils.py
querystar/exceptions.py
querystar/logger.py
querystar/remote_logger.py
querystar/settings.py
querystar/triggers/__init__.py
querystar/triggers/reddit/__init__.py
querystar/triggers/slack/__init__.py
querystar/triggers/social/__init__.py
querystar/triggers/time.py
querystar-0.3.14.dist-info/LICENSE
querystar-0.3.14.dist-info/METADATA
querystar-0.3.14.dist-info/WHEEL
querystar-0.3.14.dist-info/entry_points.txt
querystar-0.3.14.dist-info/RECORD
